salmacalculator/__init__.py
salmacalculator/calculator.py
salmacalculator-0.0.2.dist-info/LICENSE
salmacalculator-0.0.2.dist-info/METADATA
salmacalculator-0.0.2.dist-info/WHEEL
salmacalculator-0.0.2.dist-info/top_level.txt
salmacalculator-0.0.2.dist-info/RECORD
