Metadata-Version: 2.1
Name: salmacalculator
Version: 0.0.2
Summary: This is very basic calculator
Author: Salma Sultana
Author-email: 1001150@daffodil.ac
License-File: LICENSE
